autodump/__init__.py
autodump/main.py
autodump/medium/__init__.py
autodump/medium/common.py
autodump/medium/mysql_medium.py
autodump-1.0.0.dist-info/LICENSE
autodump-1.0.0.dist-info/METADATA
autodump-1.0.0.dist-info/WHEEL
autodump-1.0.0.dist-info/top_level.txt
autodump-1.0.0.dist-info/RECORD
