Metadata-Version: 2.1
Name: autodump
Version: 1.0.0
Summary: Automatically and non-invasively dump your (experiment) data
Home-page: https://github.com/noilreed/autodump
Author: Ping Z.
Author-email: ping69852@gmail.com
License: UNKNOWN
Project-URL: Bug Tracker, https://github.com/noilreed/autodump/issues
Platform: UNKNOWN
Classifier: Programming Language :: Python :: 3
Classifier: License :: OSI Approved :: MIT License
Classifier: Operating System :: OS Independent
Requires-Python: >=3.6
License-File: LICENSE
Requires-Dist: mysql-connector-python (>=8.0.25)
Requires-Dist: PyYAML
